README.md
setup.py
ColNet/__init__.py
ColNet/main.py
ColNet.egg-info/PKG-INFO
ColNet.egg-info/SOURCES.txt
ColNet.egg-info/dependency_links.txt
ColNet.egg-info/top_level.txt