Metadata-Version: 2.1
Name: ColNet
Version: 0.1
Summary: A framework!
Author: frane
Classifier: Programming Language :: Python :: 3
Classifier: License :: OSI Approved :: MIT License
Classifier: Operating System :: OS Independent
